{"information": {"Is Wanted": "Yes", "Full name": "Emma_Watson", "Age": "N/A", "Gender": "N/A", "Nationality": "N/A", "Details": "N/A", "Phone for contact": "N/A", "Photo paths": ["person_data\\Emma_Watson\\photos\\Emma_Watson_0001.jpg", "person_data\\Emma_Watson\\photos\\Emma_Watson_0002.jpg", "person_data\\Emma_Watson\\photos\\Emma_Watson_0003.jpg", "person_data\\Emma_Watson\\photos\\Emma_Watson_0004.jpg", "person_data\\Emma_Watson\\photos\\Emma_Watson_0005.jpg"], "Count photo": 5, "Date": "N/A", "Time": "N/A"}}