{"information": {"Is Wanted": "Yes", "Full name": "Martina_McBride", "Age": "N/A", "Gender": "N/A", "Nationality": "N/A", "Details": "N/A", "Phone for contact": "N/A", "Photo paths": ["person_data\\Martina_McBride\\photos\\Martina_McBride_0001.jpg", "person_data\\Martina_McBride\\photos\\Martina_McBride_0002.jpg", "person_data\\Martina_McBride\\photos\\Martina_McBride_0003.jpg", "person_data\\Martina_McBride\\photos\\Martina_McBride_0004.jpg", "person_data\\Martina_McBride\\photos\\Martina_McBride_0005.jpg"], "Count photo": 5, "Date": "N/A", "Time": "N/A"}}