{"information": {"Is Wanted": "Yes", "Full name": "Mike_Weir", "Age": "N/A", "Gender": "N/A", "Nationality": "N/A", "Details": "N/A", "Phone for contact": "N/A", "Photo paths": ["person_data\\Mike_Weir\\photos\\Mike_Weir_0001.jpg", "person_data\\Mike_Weir\\photos\\Mike_Weir_0002.jpg", "person_data\\Mike_Weir\\photos\\Mike_Weir_0003.jpg", "person_data\\Mike_Weir\\photos\\Mike_Weir_0004.jpg", "person_data\\Mike_Weir\\photos\\Mike_Weir_0005.jpg", "person_data\\Mike_Weir\\photos\\Mike_Weir_0006.jpg", "person_data\\Mike_Weir\\photos\\Mike_Weir_0007.jpg", "person_data\\Mike_Weir\\photos\\Mike_Weir_0008.jpg", "person_data\\Mike_Weir\\photos\\Mike_Weir_0009.jpg", "person_data\\Mike_Weir\\photos\\Mike_Weir_0010.jpg", "person_data\\Mike_Weir\\photos\\Mike_Weir_0011.jpg"], "Count photo": 11, "Date": "N/A", "Time": "N/A"}}