{"information": {"Is Wanted": "Yes", "Full name": "Kate_Hudson", "Age": "N/A", "Gender": "N/A", "Nationality": "N/A", "Details": "N/A", "Phone for contact": "N/A", "Photo paths": ["person_data\\Kate_Hudson\\photos\\Kate_Hudson_0001.jpg", "person_data\\Kate_Hudson\\photos\\Kate_Hudson_0002.jpg", "person_data\\Kate_Hudson\\photos\\Kate_Hudson_0003.jpg", "person_data\\Kate_Hudson\\photos\\Kate_Hudson_0004.jpg", "person_data\\Kate_Hudson\\photos\\Kate_Hudson_0005.jpg", "person_data\\Kate_Hudson\\photos\\Kate_Hudson_0006.jpg", "person_data\\Kate_Hudson\\photos\\Kate_Hudson_0007.jpg", "person_data\\Kate_Hudson\\photos\\Kate_Hudson_0008.jpg", "person_data\\Kate_Hudson\\photos\\Kate_Hudson_0009.jpg"], "Count photo": 9, "Date": "N/A", "Time": "N/A"}}